wtfutil/__init__.py
wtfutil/fileutil.py
wtfutil/httputil.py
wtfutil/notifyutil.py
wtfutil/procutil.py
wtfutil/singleinstance.py
wtfutil/sqlutil.py
wtfutil/strutil.py
wtfutil/translateutil.py
wtfutil/util.py
wtfutil-1.2.8.dist-info/LICENSE
wtfutil-1.2.8.dist-info/METADATA
wtfutil-1.2.8.dist-info/WHEEL
wtfutil-1.2.8.dist-info/top_level.txt
wtfutil-1.2.8.dist-info/RECORD
