Metadata-Version: 2.1
Name: wtfutil
Version: 1.2.8
Summary: A Python utility.
Home-page: https://github.com/vicrack
Author: vicrack
Author-email: 18179821+ViCrack@users.noreply.github.com
Platform: any
Classifier: Topic :: Utilities
Classifier: Intended Audience :: Developers
Classifier: License :: OSI Approved :: BSD License
Classifier: Topic :: Software Development :: Libraries
Classifier: Development Status :: 5 - Production/Stable
Classifier: Operating System :: OS Independent
Classifier: Programming Language :: Python :: 2.7
Classifier: Programming Language :: Python :: 3
Classifier: Programming Language :: Python :: 3.4
Classifier: Programming Language :: Python :: 3.5
Classifier: Programming Language :: Python :: 3.6
Classifier: Programming Language :: Python :: 3.7
Classifier: Programming Language :: Python :: 3.8
Classifier: Programming Language :: Python :: 3.9
Classifier: Programming Language :: Python :: 3.10
Classifier: Programming Language :: Python :: 3.11
Classifier: Programming Language :: Python :: 3.12
Classifier: Programming Language :: Python :: Implementation :: CPython
Classifier: Programming Language :: Python :: Implementation :: PyPy
License-File: LICENSE
Requires-Dist: pymysql
Requires-Dist: faker
Requires-Dist: fake-useragent
Requires-Dist: requests
Requires-Dist: requests-cache
Requires-Dist: requests-toolbelt
Requires-Dist: tldextract
Requires-Dist: dnspython
Requires-Dist: ratelimit
Requires-Dist: rich
Requires-Dist: pycryptodome
Requires-Dist: portalocker
Requires-Dist: psutil
